gersent/__init__.py
gersent/gersent.py
gersent/test.py
gersent/wordlists/de/negative.json
gersent/wordlists/de/positive.json
gersent-0.0.6.dist-info/LICENSE
gersent-0.0.6.dist-info/METADATA
gersent-0.0.6.dist-info/WHEEL
gersent-0.0.6.dist-info/top_level.txt
gersent-0.0.6.dist-info/RECORD
