Metadata-Version: 2.1
Name: gersent
Version: 0.0.6
Summary: Simple german sentiment
Home-page: https://github.com/comnGuy/gersent
Author: Bernhard Preisler
Author-email: bpblub@gmail.com
License: UNKNOWN
Platform: UNKNOWN
Classifier: Programming Language :: Python :: 3
Classifier: License :: OSI Approved :: MIT License
Classifier: Operating System :: OS Independent
Requires-Python: >=3.6
